hollos_get_data_recursive.py
hollos_get_data_recursive-0.0.2.data/scripts/hollos_get_data_recursive.py
hollos_get_data_recursive-0.0.2.dist-info/METADATA
hollos_get_data_recursive-0.0.2.dist-info/WHEEL
hollos_get_data_recursive-0.0.2.dist-info/top_level.txt
hollos_get_data_recursive-0.0.2.dist-info/RECORD
