Metadata-Version: 2.1
Name: hollos_get_data_recursive
Version: 0.0.2
Author: Hollo
Author-email: hollo1234567890e@gmail.com
